[
{
"key": "14301630",
"text": "14:30 - 16:30",
"value": "14301630"
},
{
"key": "14301700",
"text": "14:30 - 17:00",
"value": "14301700"
},
{
"key": "09001100",
"text": "09:00 - 11:00",
"value": "09001100"
},
{
"key": "09001200",
"text": "09:00 - 12:00",
"value": "09001200"
},
{
"key": "13001600",
"text": "13:00 - 16:00",
"value": "13001600"
},
{
"key": "12001400",
"text": "12:00 - 14:00",
"value": "12001400"
},
{
"key": "08001100",
"text": "08:00 - 11:00",
"value": "08001100"
},
{
"key": "12001500",
"text": "12:00 - 15:00",
"value": "12001500"
},
{
"key": "16001900",
"text": "16:00 - 19:00",
"value": "16001900"
}
]
